[
  {
    "items": [
      {
        "modifier": "hero-horizontal",
        "indexTitle": "An inline video example",
        "link": "/",
        "tag": {
          "label": "Video"
        },
        "inline-video": {
          "dev": true,
          "provider": "brightcove",
          "originatorId": "rJtrO8EKW",
          "id": "edc29e5d-4be5-4840-b34d-c2ac42afcc21",
          "playerId": "OqdPJBXJ",
          "videoId": "edc29e5d-4be5-4840-b34d-c2ac42afcc21",
          "accountId": "6058004219001",
          "caption": "Here is a video caption for this video",
          "captionPrefix": "Video",
          "options": {},
          "posterTemplate": {
            "template": "http://e3.365dm.com/17/09/{width}x{height}/3473a86cb49601cfbf554e083ada62fff2b3f99febd994f2495b99e3c9fbaca3_4088406.jpg?20170901040145",
            "sizes": ["768x432", "1600x900"]
          },
          "aspectRatio": "16/9",
          "iframeUrl": "https://sdcfrontend.github.io/demos/amp-iframe/",
          "sdcVideoId": "EyajZhajE6qOqZO9FH0r9TRKk9CZmaV8",
          "sensitive": false,
          "autoplay": false
        }
      }
    ]
  },
  {
    "variant": "alt1",
    "items": [
      {
        "modifier": "hero-horizontal",
        "indexTitle": "Your home of live sport",
        "showSnippet": true,
        "snippet": "The home of live sport across 8 channels, with 126 live Premier League games and every F1 race",
        "significance": "breaking",
        "listingImage": {
          "type": "image",
          "template": "https://via.placeholder.com/{width}x{height}",
          "alt": "Manchester City's Argentinian striker Sergio Aguero celebrates scoring a goal during the UEFA Champions league first leg play-off football match between St",
          "caption": "Manchester City's Argentinian striker Sergio Aguero celebrates scoring a goal during the UEFA Champions league first leg play-off football match between St",
          "src": "https://uat.e.365dm.com/16/08/206x155/sergio-aguero-aguero-man-city-aguero-scores_3766300_3424114.jpg?20160818004905",
          "aspectRatio": "4/3",
          "dimensions": []
        },
        "relatedLinks": [
          {
            "label": "Get Sky Sports",
            "link": "/"
          },
          {
            "label": "Get a Now TV Pass",
            "link": "/"
          }
        ]
      },
      {
        "modifier": "hero",
        "indexTitle": "Sky TV",
        "showSnippet": true,
        "snippet": "Watch the action in Ultra HD with Sky Q or get goals and highlights straight to your mobile with the Football Score Centre and Sky Sports apps.",
        "listingImage": {
          "type": "image",
          "template": "https://via.placeholder.com/{width}x{height}",
          "alt": "Manchester City's Argentinian striker Sergio Aguero celebrates scoring a goal during the UEFA Champions league first leg play-off football match between St",
          "caption": "Manchester City's Argentinian striker Sergio Aguero celebrates scoring a goal during the UEFA Champions league first leg play-off football match between St",
          "src": "https://uat.e.365dm.com/16/08/206x155/sergio-aguero-aguero-man-city-aguero-scores_3766300_3424114.jpg?20160818004905",
          "aspectRatio": "4/3",
          "dimensions": []
        },
        "relatedLinks": [
          {
            "label": "Get Sky Sports",
            "link": "/"
          }
        ],
        "link": "/"
      },
      {
        "modifier": "hero",
        "indexTitle": "Now TV",
        "showSnippet": true,
        "snippet": "Watch Sky Sports with no contract. Only pay for the days you want with a NOW TV Sky Sports Day, Week or Month Pass.",
        "listingImage": {
          "type": "image",
          "template": "https://via.placeholder.com/{width}x{height}",
          "alt": "Manchester City's Argentinian striker Sergio Aguero celebrates scoring a goal during the UEFA Champions league first leg play-off football match between St",
          "caption": "Manchester City's Argentinian striker Sergio Aguero celebrates scoring a goal during the UEFA Champions league first leg play-off football match between St",
          "src": "https://uat.e.365dm.com/16/08/206x155/sergio-aguero-aguero-man-city-aguero-scores_3766300_3424114.jpg?20160818004905",
          "aspectRatio": "4/3",
          "dimensions": []
        },
        "relatedLinks": [
          {
            "label": "Get Now TV",
            "link": "/"
          }
        ],
        "link": "/"
      }
    ]
  },
  {
    "variant": null,
    "items": [
      {
        "template": null,
        "modifier": "hero-horizontal",
        "hidden": false,
        "type": {
          "video": true
        },
        "tag": {
          "link": "/",
          "label": "Football"
        },
        "title": "Robben: 'Sind noch nicht in Topverfassung'",
        "indexTitle": "Robben: 'Sind noch nicht in Topverfassung'",
        "significance": "breaking",
        "listingImage": {
          "type": "image",
          "template": "https://uat.e.365dm.com/16/08/{width}x{height}/sergio-aguero-aguero-man-city-aguero-scores_3766300_3424114.jpg?20160818004905",
          "alt": "Manchester City's Argentinian striker Sergio Aguero celebrates scoring a goal during the UEFA Champions league first leg play-off football match between St",
          "caption": "Manchester City's Argentinian striker Sergio Aguero celebrates scoring a goal during the UEFA Champions league first leg play-off football match between St",
          "src": "https://uat.e.365dm.com/16/08/206x155/sergio-aguero-aguero-man-city-aguero-scores_3766300_3424114.jpg?20160818004905",
          "aspectRatio": "4/3",
          "dimensions": []
        },
        "author": {
          "forename": "Jamie",
          "surname": "Rednapp",
          "image": {
            "small": "https://e2.365dm.com/13/07/1-1/40/jamie-redknapp-expert-football-opinion_2976900.jpg?20130723095047",
            "large": "https://e2.365dm.com/13/07/1-1/30/jamie-redknapp-expert-football-opinion_2976900.jpg?20130723095047"
          }
        },
        "link": "/",
        "relatedLinks": [
          {
            "label": "Related link goes here and could be quite long",
            "link": "/"
          },
          {
            "label": "Related link",
            "link": "/"
          }
        ]
      },
      {
        "template": null,
        "modifier": null,
        "type": {
          "video": true
        },
        "tag": {
          "link": "/",
          "label": "Football"
        },
        "title": "2 Robben: 'Sind noch nicht in Topverfassung'",
        "indexTitle": "China economic growth hits lowest level for three decades",
        "significance": "exclusive",
        "listingImage": {
          "type": "image",
          "template": "https://uat.e.365dm.com/16/08/{width}x{height}/sergio-aguero-aguero-man-city-aguero-scores_3766300_3424114.jpg?20160818004905",
          "alt": "Manchester City's Argentinian striker Sergio Aguero celebrates scoring a goal during the UEFA Champions league first leg play-off football match between St",
          "caption": "Manchester City's Argentinian striker Sergio Aguero celebrates scoring a goal during the UEFA Champions league first leg play-off football match between St",
          "src": "https://uat.e.365dm.com/16/08/206x155/sergio-aguero-aguero-man-city-aguero-scores_3766300_3424114.jpg?20160818004905",
          "aspectRatio": "4/3",
          "dimensions": []
        },
        "author": {
          "forename": "Jamie",
          "surname": "Rednapp",
          "image": {
            "small": "https://e2.365dm.com/13/07/1-1/40/jamie-redknapp-expert-football-opinion_2976900.jpg?20130723095047",
            "large": "https://e2.365dm.com/13/07/1-1/30/jamie-redknapp-expert-football-opinion_2976900.jpg?20130723095047"
          }
        },
        "link": "/",
        "relatedLinks": null
      },
      {
        "template": null,
        "modifier": null,
        "type": {
          "video": true
        },
        "tag": {
          "link": "/",
          "label": "Football"
        },
        "title": "Robben: 'Sind noch nicht in Topverfassung'",
        "indexTitle": "China economic growth hits lowest level for three decades",
        "significance": "sponsored",
        "listingImage": {
          "type": "image",
          "template": "https://uat.e.365dm.com/16/08/{width}x{height}/sergio-aguero-aguero-man-city-aguero-scores_3766300_3424114.jpg?20160818004905",
          "alt": "Manchester City's Argentinian striker Sergio Aguero celebrates scoring a goal during the UEFA Champions league first leg play-off football match between St",
          "caption": "Manchester City's Argentinian striker Sergio Aguero celebrates scoring a goal during the UEFA Champions league first leg play-off football match between St",
          "src": "https://uat.e.365dm.com/16/08/206x155/sergio-aguero-aguero-man-city-aguero-scores_3766300_3424114.jpg?20160818004905",
          "aspectRatio": "4/3",
          "dimensions": []
        },
        "author": {
          "forename": "Jamie",
          "surname": "Rednapp",
          "image": {
            "small": "https://e2.365dm.com/13/07/1-1/40/jamie-redknapp-expert-football-opinion_2976900.jpg?20130723095047",
            "large": "https://e2.365dm.com/13/07/1-1/30/jamie-redknapp-expert-football-opinion_2976900.jpg?20130723095047"
          }
        },
        "link": "/",
        "relatedLinks": null
      },
      {
        "template": null,
        "modifier": null,
        "type": {
          "video": true
        },
        "tag": {
          "link": "/",
          "label": "Football"
        },
        "title": "Robben: 'Sind noch nicht in Topverfassung'",
        "indexTitle": "China economic growth hits lowest level for three decades",
        "significance": "live",
        "listingImage": {
          "type": "image",
          "template": "https://uat.e.365dm.com/16/08/{width}x{height}/sergio-aguero-aguero-man-city-aguero-scores_3766300_3424114.jpg?20160818004905",
          "alt": "Manchester City's Argentinian striker Sergio Aguero celebrates scoring a goal during the UEFA Champions league first leg play-off football match between St",
          "caption": "Manchester City's Argentinian striker Sergio Aguero celebrates scoring a goal during the UEFA Champions league first leg play-off football match between St",
          "src": "https://uat.e.365dm.com/16/08/206x155/sergio-aguero-aguero-man-city-aguero-scores_3766300_3424114.jpg?20160818004905",
          "aspectRatio": "4/3",
          "dimensions": []
        },
        "author": {
          "forename": "Jamie",
          "surname": "Rednapp",
          "image": {
            "small": "https://e2.365dm.com/13/07/1-1/40/jamie-redknapp-expert-football-opinion_2976900.jpg?20130723095047",
            "large": "https://e2.365dm.com/13/07/1-1/30/jamie-redknapp-expert-football-opinion_2976900.jpg?20130723095047"
          }
        },
        "link": "/",
        "relatedLinks": null
      },
      {
        "template": null,
        "modifier": null,
        "type": {
          "video": true
        },
        "tag": {
          "link": "/",
          "label": "Football"
        },
        "title": "Robben: 'Sind noch nicht in Topverfassung'",
        "indexTitle": "China economic growth hits lowest level for three decades",
        "significance": "analysis",
        "listingImage": {
          "type": "image",
          "template": "https://uat.e.365dm.com/16/08/{width}x{height}/sergio-aguero-aguero-man-city-aguero-scores_3766300_3424114.jpg?20160818004905",
          "alt": "Manchester City's Argentinian striker Sergio Aguero celebrates scoring a goal during the UEFA Champions league first leg play-off football match between St",
          "caption": "Manchester City's Argentinian striker Sergio Aguero celebrates scoring a goal during the UEFA Champions league first leg play-off football match between St",
          "src": "https://uat.e.365dm.com/16/08/206x155/sergio-aguero-aguero-man-city-aguero-scores_3766300_3424114.jpg?20160818004905",
          "aspectRatio": "4/3",
          "dimensions": []
        },
        "author": {
          "forename": "Jamie",
          "surname": "Rednapp",
          "image": {
            "small": "https://e2.365dm.com/13/07/1-1/40/jamie-redknapp-expert-football-opinion_2976900.jpg?20130723095047",
            "large": "https://e2.365dm.com/13/07/1-1/30/jamie-redknapp-expert-football-opinion_2976900.jpg?20130723095047"
          }
        },
        "link": "/",
        "relatedLinks": null
      },
      {
        "template": null,
        "modifier": null,
        "type": {
          "video": true
        },
        "tag": {
          "link": "/",
          "label": "Football"
        },
        "title": "Robben: 'Sind noch nicht in Topverfassung'",
        "indexTitle": "China economic growth hits lowest level for three decades",
        "significance": "transfer",
        "listingImage": {
          "type": "image",
          "template": "https://uat.e.365dm.com/16/08/{width}x{height}/sergio-aguero-aguero-man-city-aguero-scores_3766300_3424114.jpg?20160818004905",
          "alt": "Manchester City's Argentinian striker Sergio Aguero celebrates scoring a goal during the UEFA Champions league first leg play-off football match between St",
          "caption": "Manchester City's Argentinian striker Sergio Aguero celebrates scoring a goal during the UEFA Champions league first leg play-off football match between St",
          "src": "https://uat.e.365dm.com/16/08/206x155/sergio-aguero-aguero-man-city-aguero-scores_3766300_3424114.jpg?20160818004905",
          "aspectRatio": "4/3",
          "dimensions": []
        },
        "author": {
          "forename": "Jamie",
          "surname": "Rednapp",
          "image": {
            "small": "https://e2.365dm.com/13/07/1-1/40/jamie-redknapp-expert-football-opinion_2976900.jpg?20130723095047",
            "large": "https://e2.365dm.com/13/07/1-1/30/jamie-redknapp-expert-football-opinion_2976900.jpg?20130723095047"
          }
        },
        "link": "/",
        "relatedLinks": null
      },
      {
        "template": null,
        "modifier": null,
        "type": {
          "video": true
        },
        "tag": {
          "link": "/",
          "label": "Football"
        },
        "title": "Robben: 'Sind noch nicht in Topverfassung'",
        "indexTitle": "China economic growth hits lowest level for three decades",
        "significance": "update",
        "listingImage": {
          "type": "image",
          "template": "https://uat.e.365dm.com/16/08/{width}x{height}/sergio-aguero-aguero-man-city-aguero-scores_3766300_3424114.jpg?20160818004905",
          "alt": "Manchester City's Argentinian striker Sergio Aguero celebrates scoring a goal during the UEFA Champions league first leg play-off football match between St",
          "caption": "Manchester City's Argentinian striker Sergio Aguero celebrates scoring a goal during the UEFA Champions league first leg play-off football match between St",
          "src": "https://uat.e.365dm.com/16/08/206x155/sergio-aguero-aguero-man-city-aguero-scores_3766300_3424114.jpg?20160818004905",
          "aspectRatio": "4/3",
          "dimensions": []
        },
        "author": {
          "forename": "Jamie",
          "surname": "Rednapp",
          "image": {
            "small": "https://e2.365dm.com/13/07/1-1/40/jamie-redknapp-expert-football-opinion_2976900.jpg?20130723095047",
            "large": "https://e2.365dm.com/13/07/1-1/30/jamie-redknapp-expert-football-opinion_2976900.jpg?20130723095047"
          }
        },
        "link": "/",
        "related": null
      }
    ]
  },
  {
    "variant": "alt9",
    "items": [
      {
        "template": null,
        "modifier": null,
        "hidden": false,
        "type": {
          "video": true
        },
        "tag": {
          "link": "/",
          "label": "Football"
        },
        "title": "2 Robben: 'Sind noch nicht in Topverfassung'",
        "indexTitle": "2 Robben: 'Sind noch nicht in Topverfassung'",
        "significance": "breaking",
        "listingImage": {
          "type": "image",
          "template": "https://uat.e.365dm.com/16/08/{width}x{height}/sergio-aguero-aguero-man-city-aguero-scores_3766300_3424114.jpg?20160818004905",
          "alt": "Manchester City's Argentinian striker Sergio Aguero celebrates scoring a goal during the UEFA Champions league first leg play-off football match between St",
          "caption": "Manchester City's Argentinian striker Sergio Aguero celebrates scoring a goal during the UEFA Champions league first leg play-off football match between St",
          "src": "https://uat.e.365dm.com/16/08/206x155/sergio-aguero-aguero-man-city-aguero-scores_3766300_3424114.jpg?20160818004905",
          "aspectRatio": "4/3",
          "dimensions": []
        },
        "author": {
          "forename": "Jamie",
          "surname": "Rednapp",
          "image": {
            "small": "https://e2.365dm.com/13/07/1-1/40/jamie-redknapp-expert-football-opinion_2976900.jpg?20130723095047",
            "large": "https://e2.365dm.com/13/07/1-1/30/jamie-redknapp-expert-football-opinion_2976900.jpg?20130723095047"
          }
        },
        "link": "/",
        "related": [
          {
            "label": "Related link goes here and could be quite long",
            "link": "/"
          },
          {
            "label": "Related link",
            "link": "/"
          }
        ]
      },
      {
        "template": null,
        "modifier": null,
        "type": {
          "video": true
        },
        "tag": {
          "link": "/",
          "label": "Football"
        },
        "title": "Robben: 'Sind noch nicht in Topverfassung'",
        "indexTitle": "China economic growth hits lowest level for three decades",
        "significance": "exclusive",
        "listingImage": {
          "type": "image",
          "template": "https://uat.e.365dm.com/16/08/{width}x{height}/sergio-aguero-aguero-man-city-aguero-scores_3766300_3424114.jpg?20160818004905",
          "alt": "Manchester City's Argentinian striker Sergio Aguero celebrates scoring a goal during the UEFA Champions league first leg play-off football match between St",
          "caption": "Manchester City's Argentinian striker Sergio Aguero celebrates scoring a goal during the UEFA Champions league first leg play-off football match between St",
          "src": "https://uat.e.365dm.com/16/08/206x155/sergio-aguero-aguero-man-city-aguero-scores_3766300_3424114.jpg?20160818004905",
          "aspectRatio": "4/3",
          "dimensions": []
        },
        "author": {
          "forename": "Jamie",
          "surname": "Rednapp",
          "image": {
            "small": "https://e2.365dm.com/13/07/1-1/40/jamie-redknapp-expert-football-opinion_2976900.jpg?20130723095047",
            "large": "https://e2.365dm.com/13/07/1-1/30/jamie-redknapp-expert-football-opinion_2976900.jpg?20130723095047"
          }
        },
        "link": "/",
        "related": null
      },
      {
        "template": null,
        "modifier": null,
        "type": {
          "video": true
        },
        "tag": {
          "link": "/",
          "label": "Football"
        },
        "title": "Robben: 'Sind noch nicht in Topverfassung'",
        "indexTitle": "China economic growth hits lowest level for three decades",
        "significance": "sponsored",
        "listingImage": {
          "type": "image",
          "template": "https://uat.e.365dm.com/16/08/{width}x{height}/sergio-aguero-aguero-man-city-aguero-scores_3766300_3424114.jpg?20160818004905",
          "alt": "Manchester City's Argentinian striker Sergio Aguero celebrates scoring a goal during the UEFA Champions league first leg play-off football match between St",
          "caption": "Manchester City's Argentinian striker Sergio Aguero celebrates scoring a goal during the UEFA Champions league first leg play-off football match between St",
          "src": "https://uat.e.365dm.com/16/08/206x155/sergio-aguero-aguero-man-city-aguero-scores_3766300_3424114.jpg?20160818004905",
          "aspectRatio": "4/3",
          "dimensions": []
        },
        "author": {
          "forename": "Jamie",
          "surname": "Rednapp",
          "image": {
            "small": "https://e2.365dm.com/13/07/1-1/40/jamie-redknapp-expert-football-opinion_2976900.jpg?20130723095047",
            "large": "https://e2.365dm.com/13/07/1-1/30/jamie-redknapp-expert-football-opinion_2976900.jpg?20130723095047"
          }
        },
        "link": "/",
        "related": null
      },
      {
        "template": null,
        "modifier": null,
        "type": {
          "video": true
        },
        "tag": {
          "link": "/",
          "label": "Football"
        },
        "title": "Robben: 'Sind noch nicht in Topverfassung'",
        "indexTitle": "China economic growth hits lowest level for three decades",
        "significance": "live",
        "listingImage": {
          "type": "image",
          "template": "https://uat.e.365dm.com/16/08/{width}x{height}/sergio-aguero-aguero-man-city-aguero-scores_3766300_3424114.jpg?20160818004905",
          "alt": "Manchester City's Argentinian striker Sergio Aguero celebrates scoring a goal during the UEFA Champions league first leg play-off football match between St",
          "caption": "Manchester City's Argentinian striker Sergio Aguero celebrates scoring a goal during the UEFA Champions league first leg play-off football match between St",
          "src": "https://uat.e.365dm.com/16/08/206x155/sergio-aguero-aguero-man-city-aguero-scores_3766300_3424114.jpg?20160818004905",
          "aspectRatio": "4/3",
          "dimensions": []
        },
        "author": {
          "forename": "Jamie",
          "surname": "Rednapp",
          "image": {
            "small": "https://e2.365dm.com/13/07/1-1/40/jamie-redknapp-expert-football-opinion_2976900.jpg?20130723095047",
            "large": "https://e2.365dm.com/13/07/1-1/30/jamie-redknapp-expert-football-opinion_2976900.jpg?20130723095047"
          }
        },
        "link": "/",
        "related": null
      },
      {
        "template": null,
        "modifier": null,
        "type": {
          "video": true
        },
        "tag": {
          "link": "/",
          "label": "Football"
        },
        "title": "Robben: 'Sind noch nicht in Topverfassung'",
        "indexTitle": "China economic growth hits lowest level for three decades",
        "significance": "analysis",
        "listingImage": {
          "type": "image",
          "template": "https://uat.e.365dm.com/16/08/{width}x{height}/sergio-aguero-aguero-man-city-aguero-scores_3766300_3424114.jpg?20160818004905",
          "alt": "Manchester City's Argentinian striker Sergio Aguero celebrates scoring a goal during the UEFA Champions league first leg play-off football match between St",
          "caption": "Manchester City's Argentinian striker Sergio Aguero celebrates scoring a goal during the UEFA Champions league first leg play-off football match between St",
          "src": "https://uat.e.365dm.com/16/08/206x155/sergio-aguero-aguero-man-city-aguero-scores_3766300_3424114.jpg?20160818004905",
          "aspectRatio": "4/3",
          "dimensions": []
        },
        "author": {
          "forename": "Jamie",
          "surname": "Rednapp",
          "image": {
            "small": "https://e2.365dm.com/13/07/1-1/40/jamie-redknapp-expert-football-opinion_2976900.jpg?20130723095047",
            "large": "https://e2.365dm.com/13/07/1-1/30/jamie-redknapp-expert-football-opinion_2976900.jpg?20130723095047"
          }
        },
        "link": "/",
        "related": null
      },
      {
        "template": null,
        "modifier": null,
        "type": {
          "video": true
        },
        "tag": {
          "link": "/",
          "label": "Football"
        },
        "title": "Robben: 'Sind noch nicht in Topverfassung'",
        "indexTitle": "China economic growth hits lowest level for three decades",
        "significance": "transfer",
        "listingImage": {
          "type": "image",
          "template": "https://uat.e.365dm.com/16/08/{width}x{height}/sergio-aguero-aguero-man-city-aguero-scores_3766300_3424114.jpg?20160818004905",
          "alt": "Manchester City's Argentinian striker Sergio Aguero celebrates scoring a goal during the UEFA Champions league first leg play-off football match between St",
          "caption": "Manchester City's Argentinian striker Sergio Aguero celebrates scoring a goal during the UEFA Champions league first leg play-off football match between St",
          "src": "https://uat.e.365dm.com/16/08/206x155/sergio-aguero-aguero-man-city-aguero-scores_3766300_3424114.jpg?20160818004905",
          "aspectRatio": "4/3",
          "dimensions": []
        },
        "author": {
          "forename": "Jamie",
          "surname": "Rednapp",
          "image": {
            "small": "https://e2.365dm.com/13/07/1-1/40/jamie-redknapp-expert-football-opinion_2976900.jpg?20130723095047",
            "large": "https://e2.365dm.com/13/07/1-1/30/jamie-redknapp-expert-football-opinion_2976900.jpg?20130723095047"
          }
        },
        "link": "/",
        "related": null
      }
    ]
  },
  {
    "variant": "alt3",
    "items": [
      {
        "template": null,
        "modifier": null,
        "hidden": false,
        "type": {
          "video": true
        },
        "tag": {
          "link": "/",
          "label": "Football"
        },
        "title": "2 Robben: 'Sind noch nicht in Topverfassung'",
        "indexTitle": "2 Robben: 'Sind noch nicht in Topverfassung'",
        "significance": "breaking",
        "listingImage": {
          "type": "image",
          "template": "https://uat.e.365dm.com/16/08/{width}x{height}/sergio-aguero-aguero-man-city-aguero-scores_3766300_3424114.jpg?20160818004905",
          "alt": "Manchester City's Argentinian striker Sergio Aguero celebrates scoring a goal during the UEFA Champions league first leg play-off football match between St",
          "caption": "Manchester City's Argentinian striker Sergio Aguero celebrates scoring a goal during the UEFA Champions league first leg play-off football match between St",
          "src": "https://uat.e.365dm.com/16/08/206x155/sergio-aguero-aguero-man-city-aguero-scores_3766300_3424114.jpg?20160818004905",
          "aspectRatio": "4/3",
          "dimensions": []
        },
        "author": {
          "forename": "Jamie",
          "surname": "Rednapp",
          "image": {
            "small": "https://e2.365dm.com/13/07/1-1/40/jamie-redknapp-expert-football-opinion_2976900.jpg?20130723095047",
            "large": "https://e2.365dm.com/13/07/1-1/30/jamie-redknapp-expert-football-opinion_2976900.jpg?20130723095047"
          }
        },
        "link": "/",
        "related": [
          {
            "label": "Related link goes here and could be quite long",
            "link": "/"
          },
          {
            "label": "Related link",
            "link": "/"
          }
        ]
      },
      {
        "template": null,
        "modifier": null,
        "type": {
          "video": true
        },
        "tag": {
          "link": "/",
          "label": "Football"
        },
        "title": "Robben: 'Sind noch nicht in Topverfassung'",
        "indexTitle": "China economic growth hits lowest level for three decades",
        "significance": "update",
        "listingImage": {
          "type": "image",
          "template": "https://uat.e.365dm.com/16/08/{width}x{height}/sergio-aguero-aguero-man-city-aguero-scores_3766300_3424114.jpg?20160818004905",
          "alt": "Manchester City's Argentinian striker Sergio Aguero celebrates scoring a goal during the UEFA Champions league first leg play-off football match between St",
          "caption": "Manchester City's Argentinian striker Sergio Aguero celebrates scoring a goal during the UEFA Champions league first leg play-off football match between St",
          "src": "https://uat.e.365dm.com/16/08/206x155/sergio-aguero-aguero-man-city-aguero-scores_3766300_3424114.jpg?20160818004905",
          "aspectRatio": "4/3",
          "dimensions": []
        },
        "author": {
          "forename": "Jamie",
          "surname": "Rednapp",
          "image": {
            "small": "https://e2.365dm.com/13/07/1-1/40/jamie-redknapp-expert-football-opinion_2976900.jpg?20130723095047",
            "large": "https://e2.365dm.com/13/07/1-1/30/jamie-redknapp-expert-football-opinion_2976900.jpg?20130723095047"
          }
        },
        "link": "/",
        "related": null
      },
      {
        "template": null,
        "modifier": null,
        "type": {
          "video": true
        },
        "tag": {
          "link": "/",
          "label": "Football"
        },
        "title": "Robben: 'Sind noch nicht in Topverfassung'",
        "indexTitle": "China economic growth hits lowest level for three decades",
        "significance": "exclusive",
        "listingImage": {
          "type": "image",
          "template": "https://uat.e.365dm.com/16/08/{width}x{height}/sergio-aguero-aguero-man-city-aguero-scores_3766300_3424114.jpg?20160818004905",
          "alt": "Manchester City's Argentinian striker Sergio Aguero celebrates scoring a goal during the UEFA Champions league first leg play-off football match between St",
          "caption": "Manchester City's Argentinian striker Sergio Aguero celebrates scoring a goal during the UEFA Champions league first leg play-off football match between St",
          "src": "https://uat.e.365dm.com/16/08/206x155/sergio-aguero-aguero-man-city-aguero-scores_3766300_3424114.jpg?20160818004905",
          "aspectRatio": "4/3",
          "dimensions": []
        },
        "author": {
          "forename": "Jamie",
          "surname": "Rednapp",
          "image": {
            "small": "https://e2.365dm.com/13/07/1-1/40/jamie-redknapp-expert-football-opinion_2976900.jpg?20130723095047",
            "large": "https://e2.365dm.com/13/07/1-1/30/jamie-redknapp-expert-football-opinion_2976900.jpg?20130723095047"
          }
        },
        "link": "/",
        "related": null
      },
      {
        "template": null,
        "modifier": null,
        "type": {
          "video": true
        },
        "tag": {
          "link": "/",
          "label": "Football"
        },
        "title": "Robben: 'Sind noch nicht in Topverfassung'",
        "indexTitle": "China economic growth hits lowest level for three decades",
        "significance": "sponsored",
        "listingImage": {
          "type": "image",
          "template": "https://uat.e.365dm.com/16/08/{width}x{height}/sergio-aguero-aguero-man-city-aguero-scores_3766300_3424114.jpg?20160818004905",
          "alt": "Manchester City's Argentinian striker Sergio Aguero celebrates scoring a goal during the UEFA Champions league first leg play-off football match between St",
          "caption": "Manchester City's Argentinian striker Sergio Aguero celebrates scoring a goal during the UEFA Champions league first leg play-off football match between St",
          "src": "https://uat.e.365dm.com/16/08/206x155/sergio-aguero-aguero-man-city-aguero-scores_3766300_3424114.jpg?20160818004905",
          "aspectRatio": "4/3",
          "dimensions": []
        },
        "author": {
          "forename": "Jamie",
          "surname": "Rednapp",
          "image": {
            "small": "https://e2.365dm.com/13/07/1-1/40/jamie-redknapp-expert-football-opinion_2976900.jpg?20130723095047",
            "large": "https://e2.365dm.com/13/07/1-1/30/jamie-redknapp-expert-football-opinion_2976900.jpg?20130723095047"
          }
        },
        "link": "/",
        "related": null
      },
      {
        "template": null,
        "modifier": null,
        "type": {
          "video": true
        },
        "tag": {
          "link": "/",
          "label": "Football"
        },
        "title": "Robben: 'Sind noch nicht in Topverfassung'",
        "indexTitle": "China economic growth hits lowest level for three decades",
        "listingImage": {
          "type": "image",
          "template": "https://uat.e.365dm.com/16/08/{width}x{height}/sergio-aguero-aguero-man-city-aguero-scores_3766300_3424114.jpg?20160818004905",
          "alt": "Manchester City's Argentinian striker Sergio Aguero celebrates scoring a goal during the UEFA Champions league first leg play-off football match between St",
          "caption": "Manchester City's Argentinian striker Sergio Aguero celebrates scoring a goal during the UEFA Champions league first leg play-off football match between St",
          "src": "https://uat.e.365dm.com/16/08/206x155/sergio-aguero-aguero-man-city-aguero-scores_3766300_3424114.jpg?20160818004905",
          "aspectRatio": "4/3",
          "dimensions": []
        },
        "author": {
          "forename": "Jamie",
          "surname": "Rednapp",
          "image": {
            "small": "https://e2.365dm.com/13/07/1-1/40/jamie-redknapp-expert-football-opinion_2976900.jpg?20130723095047",
            "large": "https://e2.365dm.com/13/07/1-1/30/jamie-redknapp-expert-football-opinion_2976900.jpg?20130723095047"
          }
        },
        "link": "/",
        "related": null
      }
    ]
  },
  {
    "variant": "alt2",
    "items": [
      {
        "template": null,
        "modifier": "hero-horizontal hero-horizontal-t2",
        "hidden": false,
        "type": {
          "video": true
        },
        "tag": {
          "link": "/",
          "label": "Football"
        },
        "title": "2 Robben: 'Sind noch nicht in Topverfassung'",
        "indexTitle": "2 Robben: 'Sind noch nicht in Topverfassung'",
        "listingImage": {
          "type": "image",
          "template": "https://uat.e.365dm.com/16/08/{width}x{height}/sergio-aguero-aguero-man-city-aguero-scores_3766300_3424114.jpg?20160818004905",
          "alt": "Manchester City's Argentinian striker Sergio Aguero celebrates scoring a goal during the UEFA Champions league first leg play-off football match between St",
          "caption": "Manchester City's Argentinian striker Sergio Aguero celebrates scoring a goal during the UEFA Champions league first leg play-off football match between St",
          "src": "https://uat.e.365dm.com/16/08/206x155/sergio-aguero-aguero-man-city-aguero-scores_3766300_3424114.jpg?20160818004905",
          "aspectRatio": "4/3",
          "dimensions": []
        },
        "author": {
          "forename": "Jamie",
          "surname": "Rednapp",
          "image": {
            "small": "https://e2.365dm.com/13/07/1-1/40/jamie-redknapp-expert-football-opinion_2976900.jpg?20130723095047",
            "large": "https://e2.365dm.com/13/07/1-1/30/jamie-redknapp-expert-football-opinion_2976900.jpg?20130723095047"
          }
        },
        "link": "/",
        "related": [
          {
            "label": "Related link goes here and could be quite long",
            "link": "/"
          },
          {
            "label": "Related link",
            "link": "/"
          }
        ]
      },
      {
        "template": null,
        "modifier": "hero-horizontal hero-horizontal-t2",
        "type": {
          "video": true
        },
        "tag": {
          "link": "/",
          "label": "Football"
        },
        "title": "Robben: 'Sind noch nicht in Topverfassung'",
        "indexTitle": "China economic growth hits lowest level for three decades",
        "significance": "live",
        "listingImage": {
          "type": "image",
          "template": "https://uat.e.365dm.com/16/08/{width}x{height}/sergio-aguero-aguero-man-city-aguero-scores_3766300_3424114.jpg?20160818004905",
          "alt": "Manchester City's Argentinian striker Sergio Aguero celebrates scoring a goal during the UEFA Champions league first leg play-off football match between St",
          "caption": "Manchester City's Argentinian striker Sergio Aguero celebrates scoring a goal during the UEFA Champions league first leg play-off football match between St",
          "src": "https://uat.e.365dm.com/16/08/206x155/sergio-aguero-aguero-man-city-aguero-scores_3766300_3424114.jpg?20160818004905",
          "aspectRatio": "4/3",
          "dimensions": []
        },
        "author": {
          "forename": "Jamie",
          "surname": "Rednapp",
          "image": {
            "small": "https://e2.365dm.com/13/07/1-1/40/jamie-redknapp-expert-football-opinion_2976900.jpg?20130723095047",
            "large": "https://e2.365dm.com/13/07/1-1/30/jamie-redknapp-expert-football-opinion_2976900.jpg?20130723095047"
          }
        },
        "link": "/",
        "related": null
      }
    ]
  },
  {
    "variant": "alt2",
    "hideTags": true,
    "items": [
      {
        "template": null,
        "modifier": "hero-horizontal hero-horizontal-t2",
        "hidden": false,
        "type": {
          "video": true
        },
        "tag": {
          "link": "/",
          "label": "Football"
        },
        "title": "2 Robben: 'Sind noch nicht in Topverfassung'",
        "indexTitle": "2 Robben: 'Sind noch nicht in Topverfassung'",
        "listingImage": {
          "type": "image",
          "template": "https://uat.e.365dm.com/16/08/{width}x{height}/sergio-aguero-aguero-man-city-aguero-scores_3766300_3424114.jpg?20160818004905",
          "alt": "Manchester City's Argentinian striker Sergio Aguero celebrates scoring a goal during the UEFA Champions league first leg play-off football match between St",
          "caption": "Manchester City's Argentinian striker Sergio Aguero celebrates scoring a goal during the UEFA Champions league first leg play-off football match between St",
          "src": "https://uat.e.365dm.com/16/08/206x155/sergio-aguero-aguero-man-city-aguero-scores_3766300_3424114.jpg?20160818004905",
          "aspectRatio": "4/3",
          "dimensions": []
        },
        "author": {
          "forename": "Jamie",
          "surname": "Rednapp",
          "image": {
            "small": "https://e2.365dm.com/13/07/1-1/40/jamie-redknapp-expert-football-opinion_2976900.jpg?20130723095047",
            "large": "https://e2.365dm.com/13/07/1-1/30/jamie-redknapp-expert-football-opinion_2976900.jpg?20130723095047"
          }
        },
        "link": "/",
        "related": [
          {
            "label": "Related link goes here and could be quite long",
            "link": "/"
          },
          {
            "label": "Related link",
            "link": "/"
          }
        ]
      },
      {
        "template": null,
        "modifier": "hero-horizontal hero-horizontal-t2",
        "type": {
          "video": true
        },
        "tag": {
          "link": "/",
          "label": "Football"
        },
        "title": "Robben: 'Sind noch nicht in Topverfassung'",
        "indexTitle": "China economic growth hits lowest level for three decades",
        "significance": "live",
        "listingImage": {
          "type": "image",
          "template": "https://uat.e.365dm.com/16/08/{width}x{height}/sergio-aguero-aguero-man-city-aguero-scores_3766300_3424114.jpg?20160818004905",
          "alt": "Manchester City's Argentinian striker Sergio Aguero celebrates scoring a goal during the UEFA Champions league first leg play-off football match between St",
          "caption": "Manchester City's Argentinian striker Sergio Aguero celebrates scoring a goal during the UEFA Champions league first leg play-off football match between St",
          "src": "https://uat.e.365dm.com/16/08/206x155/sergio-aguero-aguero-man-city-aguero-scores_3766300_3424114.jpg?20160818004905",
          "aspectRatio": "4/3",
          "dimensions": []
        },
        "author": {
          "forename": "Jamie",
          "surname": "Rednapp",
          "image": {
            "small": "https://e2.365dm.com/13/07/1-1/40/jamie-redknapp-expert-football-opinion_2976900.jpg?20130723095047",
            "large": "https://e2.365dm.com/13/07/1-1/30/jamie-redknapp-expert-football-opinion_2976900.jpg?20130723095047"
          }
        },
        "link": "/",
        "related": null
      }
    ]
  }
]